package/__init__.py
package/test.py
hydroclassifation-0.3.dist-info/LICENSE
hydroclassifation-0.3.dist-info/METADATA
hydroclassifation-0.3.dist-info/WHEEL
hydroclassifation-0.3.dist-info/top_level.txt
hydroclassifation-0.3.dist-info/RECORD
