Metadata-Version: 2.1
Name: hydroclassifation
Version: 0.3
Summary: Package for hydrogeological classifcation
Author: Brayan A. Quiceno
License-File: LICENSE
Requires-Dist: numpy
Requires-Dist: pandas
